{"data":[{"codparticipant":39265566,"jugador":"HECTOR","dorsal":2,"any":2011,"codequip":7024783,"nom_equip":"DIAGONAL CLUB ESP. A","escut":"00100_0000484899_DIAGONAL_CLUB_ESPORTIU_copia.png","minut":29,"jornada":1,"tipus":"normal"},{"codparticipant":39265566,"jugador":"HECTOR","dorsal":2,"any":2011,"codequip":7024783,"nom_equip":"DIAGONAL CLUB ESP. A","escut":"00100_0000484899_DIAGONAL_CLUB_ESPORTIU_copia.png","minut":43,"jornada":1,"tipus":"normal"},{"codparticipant":39496832,"jugador":"FERNANDO","dorsal":4,"any":2011,"codequip":7024783,"nom_equip":"DIAGONAL CLUB ESP. A","escut":"00100_0000484899_DIAGONAL_CLUB_ESPORTIU_copia.png","minut":44,"jornada":1,"tipus":"normal"},{"codparticipant":45317501,"jugador":"YEHOR","dorsal":6,"any":2011,"codequip":7024783,"nom_equip":"DIAGONAL CLUB ESP. A","escut":"00100_0000484899_DIAGONAL_CLUB_ESPORTIU_copia.png","minut":58,"jornada":1,"tipus":"normal"},{"codparticipant":35966462,"jugador":"BRUNO","dorsal":9,"any":2011,"codequip":7024783,"nom_equip":"DIAGONAL CLUB ESP. A","escut":"00100_0000484899_DIAGONAL_CLUB_ESPORTIU_copia.png","minut":2,"jornada":2,"tipus":"normal"},{"codparticipant":39265566,"jugador":"HECTOR","dorsal":2,"any":2011,"codequip":7024783,"nom_equip":"DIAGONAL CLUB ESP. A","escut":"00100_0000484899_DIAGONAL_CLUB_ESPORTIU_copia.png","minut":25,"jornada":2,"tipus":"normal"},{"codparticipant":39265566,"jugador":"HECTOR","dorsal":2,"any":2011,"codequip":7024783,"nom_equip":"DIAGONAL CLUB ESP. A","escut":"00100_0000484899_DIAGONAL_CLUB_ESPORTIU_copia.png","minut":27,"jornada":2,"tipus":"normal"},{"codparticipant":45317501,"jugador":"YEHOR","dorsal":6,"any":2011,"codequip":7024783,"nom_equip":"DIAGONAL CLUB ESP. A","escut":"00100_0000484899_DIAGONAL_CLUB_ESPORTIU_copia.png","minut":59,"jornada":2,"tipus":"normal"},{"codparticipant":45317501,"jugador":"YEHOR","dorsal":6,"any":2011,"codequip":7024783,"nom_equip":"DIAGONAL CLUB ESP. A","escut":"00100_0000484899_DIAGONAL_CLUB_ESPORTIU_copia.png","minut":17,"jornada":3,"tipus":"normal"},{"codparticipant":39265566,"jugador":"HECTOR","dorsal":2,"any":2011,"codequip":7024783,"nom_equip":"DIAGONAL CLUB ESP. A","escut":"00100_0000484899_DIAGONAL_CLUB_ESPORTIU_copia.png","minut":5,"jornada":4,"tipus":"normal"},{"codparticipant":39087263,"jugador":"MAX","dorsal":11,"any":2011,"codequip":7024783,"nom_equip":"DIAGONAL CLUB ESP. A","escut":"00100_0000484899_DIAGONAL_CLUB_ESPORTIU_copia.png","minut":13,"jornada":4,"tipus":"normal"},{"codparticipant":39087263,"jugador":"MAX","dorsal":11,"any":2011,"codequip":7024783,"nom_equip":"DIAGONAL CLUB ESP. A","escut":"00100_0000484899_DIAGONAL_CLUB_ESPORTIU_copia.png","minut":19,"jornada":4,"tipus":"normal"},{"codparticipant":39496832,"jugador":"FERNANDO","dorsal":4,"any":2011,"codequip":7024783,"nom_equip":"DIAGONAL CLUB ESP. A","escut":"00100_0000484899_DIAGONAL_CLUB_ESPORTIU_copia.png","minut":24,"jornada":4,"tipus":"normal"},{"codparticipant":45049471,"jugador":"GUIU","dorsal":17,"any":2011,"codequip":7024783,"nom_equip":"DIAGONAL CLUB ESP. A","escut":"00100_0000484899_DIAGONAL_CLUB_ESPORTIU_copia.png","minut":53,"jornada":4,"tipus":"normal"},{"codparticipant":39496832,"jugador":"FERNANDO","dorsal":4,"any":2011,"codequip":7024783,"nom_equip":"DIAGONAL CLUB ESP. A","escut":"00100_0000484899_DIAGONAL_CLUB_ESPORTIU_copia.png","minut":53,"jornada":5,"tipus":"normal"},{"codparticipant":39265566,"jugador":"HECTOR","dorsal":2,"any":2011,"codequip":7024783,"nom_equip":"DIAGONAL CLUB ESP. A","escut":"00100_0000484899_DIAGONAL_CLUB_ESPORTIU_copia.png","minut":3,"jornada":6,"tipus":"normal"},{"codparticipant":45317501,"jugador":"YEHOR","dorsal":10,"any":2011,"codequip":7024783,"nom_equip":"DIAGONAL CLUB ESP. A","escut":"00100_0000484899_DIAGONAL_CLUB_ESPORTIU_copia.png","minut":37,"jornada":6,"tipus":"normal"},{"codparticipant":35966462,"jugador":"BRUNO","dorsal":9,"any":2011,"codequip":7024783,"nom_equip":"DIAGONAL CLUB ESP. A","escut":"00100_0000484899_DIAGONAL_CLUB_ESPORTIU_copia.png","minut":51,"jornada":6,"tipus":"penalti"},{"codparticipant":45317501,"jugador":"YEHOR","dorsal":10,"any":2011,"codequip":7024783,"nom_equip":"DIAGONAL CLUB ESP. A","escut":"00100_0000484899_DIAGONAL_CLUB_ESPORTIU_copia.png","minut":53,"jornada":6,"tipus":"normal"},{"codparticipant":45049245,"jugador":"ADRIÀ","dorsal":7,"any":2011,"codequip":7024783,"nom_equip":"DIAGONAL CLUB ESP. A","escut":"00100_0000484899_DIAGONAL_CLUB_ESPORTIU_copia.png","minut":10,"jornada":7,"tipus":"normal"},{"codparticipant":45317501,"jugador":"YEHOR","dorsal":10,"any":2011,"codequip":7024783,"nom_equip":"DIAGONAL CLUB ESP. A","escut":"00100_0000484899_DIAGONAL_CLUB_ESPORTIU_copia.png","minut":46,"jornada":7,"tipus":"normal"},{"codparticipant":45049471,"jugador":"GUIU","dorsal":17,"any":2011,"codequip":7024783,"nom_equip":"DIAGONAL CLUB ESP. A","escut":"00100_0000484899_DIAGONAL_CLUB_ESPORTIU_copia.png","minut":37,"jornada":8,"tipus":"normal"},{"codparticipant":45049245,"jugador":"ADRIÀ","dorsal":7,"any":2011,"codequip":7024783,"nom_equip":"DIAGONAL CLUB ESP. A","escut":"00100_0000484899_DIAGONAL_CLUB_ESPORTIU_copia.png","minut":38,"jornada":8,"tipus":"normal"},{"codparticipant":39265566,"jugador":"HECTOR","dorsal":2,"any":2011,"codequip":7024783,"nom_equip":"DIAGONAL CLUB ESP. A","escut":"00100_0000484899_DIAGONAL_CLUB_ESPORTIU_copia.png","minut":31,"jornada":9,"tipus":"normal"},{"codparticipant":39265566,"jugador":"HECTOR","dorsal":2,"any":2011,"codequip":7024783,"nom_equip":"DIAGONAL CLUB ESP. A","escut":"00100_0000484899_DIAGONAL_CLUB_ESPORTIU_copia.png","minut":47,"jornada":9,"tipus":"normal"},{"codparticipant":45049471,"jugador":"GUIU","dorsal":17,"any":2011,"codequip":7024783,"nom_equip":"DIAGONAL CLUB ESP. A","escut":"00100_0000484899_DIAGONAL_CLUB_ESPORTIU_copia.png","minut":56,"jornada":9,"tipus":"normal"},{"codparticipant":45317501,"jugador":"YEHOR","dorsal":10,"any":2011,"codequip":7024783,"nom_equip":"DIAGONAL CLUB ESP. A","escut":"00100_0000484899_DIAGONAL_CLUB_ESPORTIU_copia.png","minut":56,"jornada":9,"tipus":"normal"},{"codparticipant":45049245,"jugador":"ADRIÀ","dorsal":7,"any":2011,"codequip":7024783,"nom_equip":"DIAGONAL CLUB ESP. A","escut":"00100_0000484899_DIAGONAL_CLUB_ESPORTIU_copia.png","minut":51,"jornada":10,"tipus":"normal"},{"codparticipant":45049471,"jugador":"GUIU","dorsal":17,"any":2011,"codequip":7024783,"nom_equip":"DIAGONAL CLUB ESP. A","escut":"00100_0000484899_DIAGONAL_CLUB_ESPORTIU_copia.png","minut":19,"jornada":11,"tipus":"propia"},{"codparticipant":45317501,"jugador":"YEHOR","dorsal":10,"any":2011,"codequip":7024783,"nom_equip":"DIAGONAL CLUB ESP. A","escut":"00100_0000484899_DIAGONAL_CLUB_ESPORTIU_copia.png","minut":46,"jornada":11,"tipus":"normal"}],"codequip":"7024783","codgroup":"45021968","menuFollowTeams":[{"label":"Aleví A","href":"/classificacio?id=44763989"},{"label":"Aleví B","href":"/classificacio?id=45021968"},{"label":"Aleví C","href":"/classificacio?id=45021534"},{"label":"Aleví D","href":"/classificacio?id=45326344"},{"label":"Aleví E","href":"/classificacio?id=45330942"}]}