{"data":{"INFO":{"CODGRUPO":"45021968","GOLES_CASA":"3","GOLES_FUERA":"5","PENALTIS_CASA":null,"PENALTIS_FUERA":null,"CODACTA":"3037916","COD_COMPETICION":43990541,"NOM_COMPETICION":"ALEVÍ SEGONA DIVISIÓ","NOM_COMPETICION_URL":"alevi-segona-divisio","COD_GRUPO":45021968,"GRUPO":"GRUP 18","GRUPO_URL":"grup-18","CODEQUIPO_CASA":"40077","CODEQUIPO_FUERA":"36903","JORNADA":"26","CODIGO_CAMPO":"515","COMIENZO1":"2023-05-07 09:00:00","SUSPENDIDO":"0","NOMBRE":"CAMP DE FUTBOL MPAL. NARCÍS SALA","DIRECCION":"c/ de Santa Coloma, 39","TEMP_NOMBRE":"2223","TEMP_LARGO":"TEMPORADA 2022-2023","CIUDAD":"Barcelona","ESTADO":"4"},"ARBITROS":[{"CODTIPO_ARBITRO":"1","CODARBITRO":"3388417","NOMBRE_ARBITRO":"ALVARO ENRIQUE","NOMBRE":"Barcelona3"}],"GOLES":[{"NOMBRE":"MARC","LICENCIA":"20","DORSAL":"5","CODPARTICIPANTE":"33201894","FECHA_NACIMIENTO":2,"PORTERO":null,"TIPO":"normal","MINUTO":"8","EQUIPO":"visitante"},{"NOMBRE":"NIL","LICENCIA":"20","DORSAL":"9","CODPARTICIPANTE":"36367428","FECHA_NACIMIENTO":2,"PORTERO":null,"TIPO":"normal","MINUTO":"47","EQUIPO":"visitante"},{"NOMBRE":"NIL","LICENCIA":"20","DORSAL":"9","CODPARTICIPANTE":"36367428","FECHA_NACIMIENTO":2,"PORTERO":null,"TIPO":"normal","MINUTO":"51","EQUIPO":"visitante"},{"NOMBRE":"NIL","LICENCIA":"20","DORSAL":"9","CODPARTICIPANTE":"36367428","FECHA_NACIMIENTO":2,"PORTERO":null,"TIPO":"normal","MINUTO":"56","EQUIPO":"visitante"},{"NOMBRE":"VICTOR","LICENCIA":"20","DORSAL":"9","CODPARTICIPANTE":"36983473","FECHA_NACIMIENTO":2,"PORTERO":null,"TIPO":"normal","MINUTO":"12","EQUIPO":"local"},{"NOMBRE":"NIL","LICENCIA":"20","DORSAL":"10","CODPARTICIPANTE":"31877244","FECHA_NACIMIENTO":2,"PORTERO":null,"TIPO":"normal","MINUTO":"25","EQUIPO":"local"},{"NOMBRE":"ALEX","LICENCIA":"20","DORSAL":"10","CODPARTICIPANTE":"33020132","FECHA_NACIMIENTO":2,"PORTERO":null,"TIPO":"normal","MINUTO":"15","EQUIPO":"visitante"},{"NOMBRE":"SAMY","LICENCIA":"12","DORSAL":"70","CODPARTICIPANTE":"42040687","FECHA_NACIMIENTO":1,"PORTERO":null,"TIPO":"normal","MINUTO":"23","EQUIPO":"local"}],"EQUIPO_CASA":{"CODCLUB":1014,"CODCLUB2":1014,"CODEQUIPO":40077,"NOMBRE_CLUB":"SANT ANDREU, U.E","NOMBRE_CLUB_URL":"sant-andreu-ue","NOMBRE_EQUIPO":"SANT ANDREU, U.E E","NOMBRE_EQUIPO_URL":"sant-andreu-ue-e","NOMBRE":"00100_0000573790_standreu_200x200.png","NOMBRE_ABREVIADO_URL":"2al","CODGRUPO":41527092,"TITULARES":[{"NOMBRE":"ALEJANDRO VALENTINO","LICENCIA":"20","DORSAL":"1","CODPARTICIPANTE":"33666355","FECHA_NACIMIENTO":1,"PORTERO":1},{"NOMBRE":"RAMON","LICENCIA":"20","DORSAL":"5","CODPARTICIPANTE":"29185649","FECHA_NACIMIENTO":1,"PORTERO":null},{"NOMBRE":"MARC","LICENCIA":"20","DORSAL":"8","CODPARTICIPANTE":"33668248","FECHA_NACIMIENTO":1,"PORTERO":null},{"NOMBRE":"VICTOR","LICENCIA":"20","DORSAL":"9","CODPARTICIPANTE":"36983473","FECHA_NACIMIENTO":2,"PORTERO":null},{"NOMBRE":"NIL","LICENCIA":"20","DORSAL":"10","CODPARTICIPANTE":"31877244","FECHA_NACIMIENTO":2,"PORTERO":null},{"NOMBRE":"AKSEL","LICENCIA":"20","DORSAL":"12","CODPARTICIPANTE":"37623687","FECHA_NACIMIENTO":2,"PORTERO":null},{"NOMBRE":"BERNAT","LICENCIA":"20","DORSAL":"14","CODPARTICIPANTE":"45483586","FECHA_NACIMIENTO":1,"PORTERO":null}],"SUPLENTES":[{"NOMBRE":"FRANCESC","LICENCIA":"20","DORSAL":"6","CODPARTICIPANTE":"32634138","FECHA_NACIMIENTO":2,"PORTERO":null},{"NOMBRE":"POL","LICENCIA":"12","DORSAL":"18","CODPARTICIPANTE":"35264585","FECHA_NACIMIENTO":1,"PORTERO":null},{"NOMBRE":"SAMY","LICENCIA":"12","DORSAL":"70","CODPARTICIPANTE":"42040687","FECHA_NACIMIENTO":1,"PORTERO":null}],"COSTECNIC":{"Entrenador Titular":"CHRISTIAN"},"SUSTITUCIONES":[],"SANCIONES":[]},"EQUIPO_FUERA":{"CODCLUB":2930,"CODCLUB2":2930,"CODEQUIPO":36903,"NOMBRE_CLUB":"Pª BARC. CINC COPES","NOMBRE_CLUB_URL":"pa-barc-cinc-copes","NOMBRE_EQUIPO":"Pª BARC. CINC COPES B","NOMBRE_EQUIPO_URL":"pa-barc-cinc-copes-b","NOMBRE":"00100_0000576648_cinccopes_200x200.png","NOMBRE_ABREVIADO_URL":"2al","CODGRUPO":41526744,"TITULARES":[{"NOMBRE":"ALBERT","LICENCIA":"20","DORSAL":"1","CODPARTICIPANTE":"33996947","FECHA_NACIMIENTO":2,"PORTERO":1},{"NOMBRE":"DANIEL","LICENCIA":"20","DORSAL":"3","CODPARTICIPANTE":"39842840","FECHA_NACIMIENTO":2,"PORTERO":null},{"NOMBRE":"MARC","LICENCIA":"20","DORSAL":"5","CODPARTICIPANTE":"33201894","FECHA_NACIMIENTO":2,"PORTERO":null},{"NOMBRE":"NICOLAS","LICENCIA":"20","DORSAL":"6","CODPARTICIPANTE":"33668913","FECHA_NACIMIENTO":2,"PORTERO":null},{"NOMBRE":"DAVID","LICENCIA":"20","DORSAL":"8","CODPARTICIPANTE":"33989602","FECHA_NACIMIENTO":2,"PORTERO":null},{"NOMBRE":"NIL","LICENCIA":"20","DORSAL":"9","CODPARTICIPANTE":"36367428","FECHA_NACIMIENTO":2,"PORTERO":null},{"NOMBRE":"ALEX","LICENCIA":"20","DORSAL":"10","CODPARTICIPANTE":"33020132","FECHA_NACIMIENTO":2,"PORTERO":null}],"SUPLENTES":[{"NOMBRE":"GUILLEM","LICENCIA":"20","DORSAL":"4","CODPARTICIPANTE":"40015382","FECHA_NACIMIENTO":2,"PORTERO":null},{"NOMBRE":"BIEL","LICENCIA":"20","DORSAL":"7","CODPARTICIPANTE":"37663817","FECHA_NACIMIENTO":2,"PORTERO":null}],"COSTECNIC":{"Entrenador Titular":"MARC"},"SUSTITUCIONES":[],"SANCIONES":[]}},"codacta":"3037916","titulars_local":[{"codparticipant":33666355,"codequip":40077,"dorsal":1,"titularitats":1,"porter":1,"nom":"ALEJANDRO VALENTINO","any":2011,"partits":1,"nom_equip":"SANT ANDREU, U.E E","colorequipacio1":"#FFFF00","colorequipacio2":"#0000FF"},{"codparticipant":29185649,"codequip":40077,"dorsal":5,"titularitats":1,"porter":null,"nom":"RAMON","any":2011,"partits":1,"nom_equip":"SANT ANDREU, U.E E","colorequipacio1":"#FFFF00","colorequipacio2":"#0000FF"},{"codparticipant":32634138,"codequip":40077,"dorsal":6,"titularitats":0,"porter":null,"nom":"FRANCESC","any":2012,"partits":1,"nom_equip":"SANT ANDREU, U.E E","colorequipacio1":"#FFFF00","colorequipacio2":"#0000FF"},{"codparticipant":33668248,"codequip":40077,"dorsal":8,"titularitats":1,"porter":null,"nom":"MARC","any":2011,"partits":1,"nom_equip":"SANT ANDREU, U.E E","colorequipacio1":"#FFFF00","colorequipacio2":"#0000FF"},{"codparticipant":36983473,"codequip":40077,"dorsal":9,"titularitats":1,"porter":null,"nom":"VICTOR","any":2012,"partits":1,"nom_equip":"SANT ANDREU, U.E E","colorequipacio1":"#FFFF00","colorequipacio2":"#0000FF"},{"codparticipant":31877244,"codequip":40077,"dorsal":10,"titularitats":1,"porter":null,"nom":"NIL","any":2012,"partits":1,"nom_equip":"SANT ANDREU, U.E E","colorequipacio1":"#FFFF00","colorequipacio2":"#0000FF"},{"codparticipant":37623687,"codequip":40077,"dorsal":12,"titularitats":1,"porter":null,"nom":"AKSEL","any":2012,"partits":1,"nom_equip":"SANT ANDREU, U.E E","colorequipacio1":"#FFFF00","colorequipacio2":"#0000FF"},{"codparticipant":45483586,"codequip":40077,"dorsal":14,"titularitats":1,"porter":null,"nom":"BERNAT","any":2011,"partits":1,"nom_equip":"SANT ANDREU, U.E E","colorequipacio1":"#FFFF00","colorequipacio2":"#0000FF"},{"codparticipant":35264585,"codequip":40077,"dorsal":18,"titularitats":0,"porter":null,"nom":"POL","any":2011,"partits":1,"nom_equip":"SANT ANDREU, U.E E","colorequipacio1":"#FFFF00","colorequipacio2":"#0000FF"},{"codparticipant":42040687,"codequip":40077,"dorsal":70,"titularitats":0,"porter":null,"nom":"SAMY","any":2011,"partits":1,"nom_equip":"SANT ANDREU, U.E E","colorequipacio1":"#FFFF00","colorequipacio2":"#0000FF"}],"titulars_visitant":[{"codparticipant":33996947,"codequip":36903,"dorsal":1,"titularitats":1,"porter":1,"nom":"ALBERT","any":2012,"partits":1,"nom_equip":"Pª BARC. CINC COPES B","colorequipacio1":"#0000FF","colorequipacio2":"#FFFF00"},{"codparticipant":39842840,"codequip":36903,"dorsal":3,"titularitats":1,"porter":null,"nom":"DANIEL","any":2012,"partits":1,"nom_equip":"Pª BARC. CINC COPES B","colorequipacio1":"#0000FF","colorequipacio2":"#FFFF00"},{"codparticipant":40015382,"codequip":36903,"dorsal":4,"titularitats":0,"porter":null,"nom":"GUILLEM","any":2012,"partits":1,"nom_equip":"Pª BARC. CINC COPES B","colorequipacio1":"#0000FF","colorequipacio2":"#FFFF00"},{"codparticipant":33201894,"codequip":36903,"dorsal":5,"titularitats":1,"porter":null,"nom":"MARC","any":2012,"partits":1,"nom_equip":"Pª BARC. CINC COPES B","colorequipacio1":"#0000FF","colorequipacio2":"#FFFF00"},{"codparticipant":33668913,"codequip":36903,"dorsal":6,"titularitats":1,"porter":null,"nom":"NICOLAS","any":2012,"partits":1,"nom_equip":"Pª BARC. CINC COPES B","colorequipacio1":"#0000FF","colorequipacio2":"#FFFF00"},{"codparticipant":37663817,"codequip":36903,"dorsal":7,"titularitats":0,"porter":null,"nom":"BIEL","any":2012,"partits":1,"nom_equip":"Pª BARC. CINC COPES B","colorequipacio1":"#0000FF","colorequipacio2":"#FFFF00"},{"codparticipant":33989602,"codequip":36903,"dorsal":8,"titularitats":1,"porter":null,"nom":"DAVID","any":2012,"partits":1,"nom_equip":"Pª BARC. CINC COPES B","colorequipacio1":"#0000FF","colorequipacio2":"#FFFF00"},{"codparticipant":36367428,"codequip":36903,"dorsal":9,"titularitats":1,"porter":null,"nom":"NIL","any":2012,"partits":1,"nom_equip":"Pª BARC. CINC COPES B","colorequipacio1":"#0000FF","colorequipacio2":"#FFFF00"},{"codparticipant":33020132,"codequip":36903,"dorsal":10,"titularitats":1,"porter":null,"nom":"ALEX","any":2012,"partits":1,"nom_equip":"Pª BARC. CINC COPES B","colorequipacio1":"#0000FF","colorequipacio2":"#FFFF00"}],"menuFollowTeams":[{"label":"Aleví A","href":"/classificacio?id=44763989"},{"label":"Aleví B","href":"/classificacio?id=45021968"},{"label":"Aleví C","href":"/classificacio?id=45021534"},{"label":"Aleví D","href":"/classificacio?id=45326344"},{"label":"Aleví E","href":"/classificacio?id=45330942"}]}