{"data":{"INFO":{"CODGRUPO":"45326344","GOLES_CASA":"11","GOLES_FUERA":"3","PENALTIS_CASA":null,"PENALTIS_FUERA":null,"CODACTA":"3082854","COD_COMPETICION":43990569,"NOM_COMPETICION":"ALEVÍ TERCERA DIVISIÓ","NOM_COMPETICION_URL":"alevi-tercera-divisio","COD_GRUPO":45326344,"GRUPO":"GRUP 7","GRUPO_URL":"grup-7","CODEQUIPO_CASA":"43974946","CODEQUIPO_FUERA":"37737","JORNADA":"20","CODIGO_CAMPO":"1714","COMIENZO1":"2023-03-19 11:30:00","SUSPENDIDO":"0","NOMBRE":"CAMP DE FUTBOL SCHOOL AGORA INTERNATIONAL SANT CUGAT","DIRECCION":"c/ Ferrer i Guàrdia, s/n","TEMP_NOMBRE":"2223","TEMP_LARGO":"TEMPORADA 2022-2023","CIUDAD":"Sant Cugat Del Vallès","ESTADO":"4"},"ARBITROS":[{"CODTIPO_ARBITRO":"1","CODARBITRO":"3327578","NOMBRE_ARBITRO":"ANAS","NOMBRE":"Vallès Occidental"}],"GOLES":[{"NOMBRE":"LUCAS","LICENCIA":"20","DORSAL":"3","CODPARTICIPANTE":"42864516","FECHA_NACIMIENTO":1,"PORTERO":null,"TIPO":"normal","MINUTO":"17","EQUIPO":"local"},{"NOMBRE":"JAVIER","LICENCIA":"12","DORSAL":"6","CODPARTICIPANTE":"45672730","FECHA_NACIMIENTO":1,"PORTERO":null,"TIPO":"normal","MINUTO":"16","EQUIPO":"local"},{"NOMBRE":"TIAGO","LICENCIA":"20","DORSAL":"7","CODPARTICIPANTE":"40253163","FECHA_NACIMIENTO":1,"PORTERO":null,"TIPO":"normal","MINUTO":"23","EQUIPO":"local"},{"NOMBRE":"TIAGO","LICENCIA":"20","DORSAL":"7","CODPARTICIPANTE":"40253163","FECHA_NACIMIENTO":1,"PORTERO":null,"TIPO":"normal","MINUTO":"36","EQUIPO":"local"},{"NOMBRE":"TIAGO","LICENCIA":"20","DORSAL":"7","CODPARTICIPANTE":"40253163","FECHA_NACIMIENTO":1,"PORTERO":null,"TIPO":"normal","MINUTO":"50","EQUIPO":"local"},{"NOMBRE":"TIAGO","LICENCIA":"20","DORSAL":"7","CODPARTICIPANTE":"40253163","FECHA_NACIMIENTO":1,"PORTERO":null,"TIPO":"normal","MINUTO":"58","EQUIPO":"local"},{"NOMBRE":"MATTEO","LICENCIA":"20","DORSAL":"10","CODPARTICIPANTE":"46016982","FECHA_NACIMIENTO":1,"PORTERO":1,"TIPO":"normal","MINUTO":"31","EQUIPO":"local"},{"NOMBRE":"MATTEO","LICENCIA":"20","DORSAL":"10","CODPARTICIPANTE":"46016982","FECHA_NACIMIENTO":1,"PORTERO":1,"TIPO":"normal","MINUTO":"45","EQUIPO":"local"},{"NOMBRE":"NICOLAS","LICENCIA":"20","DORSAL":"12","CODPARTICIPANTE":"45990812","FECHA_NACIMIENTO":2,"PORTERO":null,"TIPO":"normal","MINUTO":"43","EQUIPO":"local"},{"NOMBRE":"NICOLAS","LICENCIA":"20","DORSAL":"12","CODPARTICIPANTE":"45990812","FECHA_NACIMIENTO":2,"PORTERO":null,"TIPO":"normal","MINUTO":"57","EQUIPO":"local"},{"NOMBRE":"NICOLAS","LICENCIA":"20","DORSAL":"12","CODPARTICIPANTE":"45990812","FECHA_NACIMIENTO":2,"PORTERO":null,"TIPO":"normal","MINUTO":"59","EQUIPO":"local"},{"NOMBRE":"IAN","LICENCIA":"20","DORSAL":"15","CODPARTICIPANTE":"44648531","FECHA_NACIMIENTO":2,"PORTERO":null,"TIPO":"normal","MINUTO":"3","EQUIPO":"visitante"},{"NOMBRE":"OSAYI INNOCENT","LICENCIA":"20","DORSAL":"25","CODPARTICIPANTE":"36563638","FECHA_NACIMIENTO":1,"PORTERO":null,"TIPO":"normal","MINUTO":"33","EQUIPO":"visitante"},{"NOMBRE":"JOEL","LICENCIA":"20","DORSAL":"33","CODPARTICIPANTE":"45104265","FECHA_NACIMIENTO":2,"PORTERO":null,"TIPO":"normal","MINUTO":"34","EQUIPO":"visitante"}],"EQUIPO_CASA":{"CODCLUB":6612,"CODCLUB2":43918619,"CODEQUIPO":43974946,"NOMBRE_CLUB":"VALLDOREIX, F.C.","NOMBRE_CLUB_URL":"valldoreix-fc","NOMBRE_EQUIPO":"VALLDOREIX, F.C. A","NOMBRE_EQUIPO_URL":"valldoreix-fc-a","NOMBRE":"00100_0000878137_valldoreixfc_200.png","NOMBRE_ABREVIADO_URL":"3al","CODGRUPO":45326344,"TITULARES":[{"NOMBRE":"LUCAS","LICENCIA":"20","DORSAL":"3","CODPARTICIPANTE":"42864516","FECHA_NACIMIENTO":1,"PORTERO":null},{"NOMBRE":"JAUME","LICENCIA":"20","DORSAL":"5","CODPARTICIPANTE":"37174569","FECHA_NACIMIENTO":2,"PORTERO":null},{"NOMBRE":"JAVIER","LICENCIA":"12","DORSAL":"6","CODPARTICIPANTE":"45672730","FECHA_NACIMIENTO":1,"PORTERO":null},{"NOMBRE":"TIAGO","LICENCIA":"20","DORSAL":"7","CODPARTICIPANTE":"40253163","FECHA_NACIMIENTO":1,"PORTERO":null},{"NOMBRE":"MATTEO","LICENCIA":"20","DORSAL":"10","CODPARTICIPANTE":"46016982","FECHA_NACIMIENTO":1,"PORTERO":1},{"NOMBRE":"TOMAS","LICENCIA":"20","DORSAL":"11","CODPARTICIPANTE":"45993588","FECHA_NACIMIENTO":1,"PORTERO":null},{"NOMBRE":"NUNO","LICENCIA":"20","DORSAL":"17","CODPARTICIPANTE":"41151758","FECHA_NACIMIENTO":2,"PORTERO":null}],"SUPLENTES":[{"NOMBRE":"NICOLAS","LICENCIA":"20","DORSAL":"12","CODPARTICIPANTE":"45990812","FECHA_NACIMIENTO":2,"PORTERO":null},{"NOMBRE":"ESTEBAN","LICENCIA":"20","DORSAL":"20","CODPARTICIPANTE":"46070796","FECHA_NACIMIENTO":2,"PORTERO":null}],"COSTECNIC":{"Entrenador Titular":"PABLO"},"SUSTITUCIONES":[],"SANCIONES":[]},"EQUIPO_FUERA":{"CODCLUB":1400,"CODCLUB2":1400,"CODEQUIPO":37737,"NOMBRE_CLUB":"TRINIDAD, C.D.","NOMBRE_CLUB_URL":"trinidad-cd","NOMBRE_EQUIPO":"TRINIDAD, C.D. A","NOMBRE_EQUIPO_URL":"trinidad-cd-a","NOMBRE":"00100_0000653381_trinidad_200x200.png","NOMBRE_ABREVIADO_URL":"3al","CODGRUPO":45326344,"TITULARES":[{"NOMBRE":"KEVIN","LICENCIA":"20","DORSAL":"1","CODPARTICIPANTE":"44809314","FECHA_NACIMIENTO":2,"PORTERO":1},{"NOMBRE":"HUGO","LICENCIA":"20","DORSAL":"3","CODPARTICIPANTE":"44778453","FECHA_NACIMIENTO":2,"PORTERO":null},{"NOMBRE":"IAN","LICENCIA":"20","DORSAL":"15","CODPARTICIPANTE":"44648531","FECHA_NACIMIENTO":2,"PORTERO":null},{"NOMBRE":"ANGEL","LICENCIA":"20","DORSAL":"17","CODPARTICIPANTE":"36564317","FECHA_NACIMIENTO":1,"PORTERO":null},{"NOMBRE":"OSAYANDE ANOINTED","LICENCIA":"20","DORSAL":"24","CODPARTICIPANTE":"44671888","FECHA_NACIMIENTO":2,"PORTERO":null},{"NOMBRE":"JOEL","LICENCIA":"20","DORSAL":"33","CODPARTICIPANTE":"45104265","FECHA_NACIMIENTO":2,"PORTERO":null},{"NOMBRE":"ENRIQUE","LICENCIA":"20","DORSAL":"99","CODPARTICIPANTE":"44627665","FECHA_NACIMIENTO":2,"PORTERO":null}],"SUPLENTES":[{"NOMBRE":"LEONARDO","LICENCIA":"20","DORSAL":"23","CODPARTICIPANTE":"44882062","FECHA_NACIMIENTO":1,"PORTERO":null},{"NOMBRE":"OSAYI INNOCENT","LICENCIA":"20","DORSAL":"25","CODPARTICIPANTE":"36563638","FECHA_NACIMIENTO":1,"PORTERO":null},{"NOMBRE":"DAVID","LICENCIA":"20","DORSAL":"34","CODPARTICIPANTE":"36931479","FECHA_NACIMIENTO":1,"PORTERO":null}],"COSTECNIC":{"Delegat":"DYLAN-IVAN"},"SUSTITUCIONES":[],"SANCIONES":[]}},"codacta":"3082854","titulars_local":[{"codparticipant":42864516,"codequip":43974946,"dorsal":3,"titularitats":1,"porter":null,"nom":"LUCAS","any":2011,"partits":1,"nom_equip":"VALLDOREIX, F.C. A","colorequipacio1":"#648B34","colorequipacio2":"#222222"},{"codparticipant":37174569,"codequip":43974946,"dorsal":5,"titularitats":1,"porter":null,"nom":"JAUME","any":2012,"partits":1,"nom_equip":"VALLDOREIX, F.C. A","colorequipacio1":"#648B34","colorequipacio2":"#222222"},{"codparticipant":45672730,"codequip":43974946,"dorsal":6,"titularitats":1,"porter":null,"nom":"JAVIER","any":2011,"partits":1,"nom_equip":"VALLDOREIX, F.C. A","colorequipacio1":"#648B34","colorequipacio2":"#222222"},{"codparticipant":40253163,"codequip":43974946,"dorsal":7,"titularitats":1,"porter":null,"nom":"TIAGO","any":2011,"partits":1,"nom_equip":"VALLDOREIX, F.C. A","colorequipacio1":"#648B34","colorequipacio2":"#222222"},{"codparticipant":46016982,"codequip":43974946,"dorsal":10,"titularitats":1,"porter":1,"nom":"MATTEO","any":2011,"partits":1,"nom_equip":"VALLDOREIX, F.C. A","colorequipacio1":"#648B34","colorequipacio2":"#222222"},{"codparticipant":45993588,"codequip":43974946,"dorsal":11,"titularitats":1,"porter":null,"nom":"TOMAS","any":2011,"partits":1,"nom_equip":"VALLDOREIX, F.C. A","colorequipacio1":"#648B34","colorequipacio2":"#222222"},{"codparticipant":45990812,"codequip":43974946,"dorsal":12,"titularitats":0,"porter":null,"nom":"NICOLAS","any":2012,"partits":1,"nom_equip":"VALLDOREIX, F.C. A","colorequipacio1":"#648B34","colorequipacio2":"#222222"},{"codparticipant":41151758,"codequip":43974946,"dorsal":17,"titularitats":1,"porter":null,"nom":"NUNO","any":2012,"partits":1,"nom_equip":"VALLDOREIX, F.C. A","colorequipacio1":"#648B34","colorequipacio2":"#222222"},{"codparticipant":46070796,"codequip":43974946,"dorsal":20,"titularitats":0,"porter":null,"nom":"ESTEBAN","any":2012,"partits":1,"nom_equip":"VALLDOREIX, F.C. A","colorequipacio1":"#648B34","colorequipacio2":"#222222"}],"titulars_visitant":[{"codparticipant":44809314,"codequip":37737,"dorsal":1,"titularitats":1,"porter":1,"nom":"KEVIN","any":2012,"partits":1,"nom_equip":"TRINIDAD, C.D. A","colorequipacio1":"#FF0909","colorequipacio2":"#1F1C1C"},{"codparticipant":44778453,"codequip":37737,"dorsal":3,"titularitats":1,"porter":null,"nom":"HUGO","any":2012,"partits":1,"nom_equip":"TRINIDAD, C.D. A","colorequipacio1":"#FF0909","colorequipacio2":"#1F1C1C"},{"codparticipant":44648531,"codequip":37737,"dorsal":15,"titularitats":1,"porter":null,"nom":"IAN","any":2012,"partits":1,"nom_equip":"TRINIDAD, C.D. A","colorequipacio1":"#FF0909","colorequipacio2":"#1F1C1C"},{"codparticipant":36564317,"codequip":37737,"dorsal":17,"titularitats":1,"porter":null,"nom":"ANGEL","any":2011,"partits":1,"nom_equip":"TRINIDAD, C.D. A","colorequipacio1":"#FF0909","colorequipacio2":"#1F1C1C"},{"codparticipant":44882062,"codequip":37737,"dorsal":23,"titularitats":0,"porter":null,"nom":"LEONARDO","any":2011,"partits":1,"nom_equip":"TRINIDAD, C.D. A","colorequipacio1":"#FF0909","colorequipacio2":"#1F1C1C"},{"codparticipant":44671888,"codequip":37737,"dorsal":24,"titularitats":1,"porter":null,"nom":"OSAYANDE ANOINTED","any":2012,"partits":1,"nom_equip":"TRINIDAD, C.D. A","colorequipacio1":"#FF0909","colorequipacio2":"#1F1C1C"},{"codparticipant":36563638,"codequip":37737,"dorsal":25,"titularitats":0,"porter":null,"nom":"OSAYI INNOCENT","any":2011,"partits":1,"nom_equip":"TRINIDAD, C.D. A","colorequipacio1":"#FF0909","colorequipacio2":"#1F1C1C"},{"codparticipant":45104265,"codequip":37737,"dorsal":33,"titularitats":1,"porter":null,"nom":"JOEL","any":2012,"partits":1,"nom_equip":"TRINIDAD, C.D. A","colorequipacio1":"#FF0909","colorequipacio2":"#1F1C1C"},{"codparticipant":36931479,"codequip":37737,"dorsal":34,"titularitats":0,"porter":null,"nom":"DAVID","any":2011,"partits":1,"nom_equip":"TRINIDAD, C.D. A","colorequipacio1":"#FF0909","colorequipacio2":"#1F1C1C"},{"codparticipant":44627665,"codequip":37737,"dorsal":99,"titularitats":1,"porter":null,"nom":"ENRIQUE","any":2012,"partits":1,"nom_equip":"TRINIDAD, C.D. A","colorequipacio1":"#FF0909","colorequipacio2":"#1F1C1C"}],"menuFollowTeams":[{"label":"Aleví A","href":"/classificacio?id=44763989"},{"label":"Aleví B","href":"/classificacio?id=45021968"},{"label":"Aleví C","href":"/classificacio?id=45021534"},{"label":"Aleví D","href":"/classificacio?id=45326344"},{"label":"Aleví E","href":"/classificacio?id=45330942"}]}