{"data":{"INFO":{"CODGRUPO":"45326344","GOLES_CASA":"4","GOLES_FUERA":"3","PENALTIS_CASA":null,"PENALTIS_FUERA":null,"CODACTA":"3082718","COD_COMPETICION":43990569,"NOM_COMPETICION":"ALEVÍ TERCERA DIVISIÓ","NOM_COMPETICION_URL":"alevi-tercera-divisio","COD_GRUPO":45326344,"GRUPO":"GRUP 7","GRUPO_URL":"grup-7","CODEQUIPO_CASA":"33934","CODEQUIPO_FUERA":"32324228","JORNADA":"3","CODIGO_CAMPO":"519","COMIENZO1":"2022-10-22 12:40:00","SUSPENDIDO":"0","NOMBRE":"CAMP DE FUTBOL MPAL. NOU BARRIS","DIRECCION":"Via Júlia, 170","TEMP_NOMBRE":"2223","TEMP_LARGO":"TEMPORADA 2022-2023","CIUDAD":"Barcelona","ESTADO":"4"},"ARBITROS":[{"CODTIPO_ARBITRO":"1","CODARBITRO":"9219","NOMBRE_ARBITRO":"HASEEB","NOMBRE":"Barcelona3"}],"GOLES":[{"NOMBRE":"AITOR","LICENCIA":"20","DORSAL":"2","CODPARTICIPANTE":"39808118","FECHA_NACIMIENTO":2,"PORTERO":null,"TIPO":"propia","MINUTO":"29","EQUIPO":"visitante"},{"NOMBRE":"BERNAT","LICENCIA":"20","DORSAL":"3","CODPARTICIPANTE":"33826069","FECHA_NACIMIENTO":2,"PORTERO":null,"TIPO":"propia","MINUTO":"58","EQUIPO":"visitante"},{"NOMBRE":"PAU","LICENCIA":"20","DORSAL":"5","CODPARTICIPANTE":"33987702","FECHA_NACIMIENTO":2,"PORTERO":null,"TIPO":"propia","MINUTO":"7","EQUIPO":"visitante"},{"NOMBRE":"CRISTHIAN VINICIUS","LICENCIA":"20","DORSAL":"7","CODPARTICIPANTE":"39738138","FECHA_NACIMIENTO":2,"PORTERO":null,"TIPO":"normal","MINUTO":"22","EQUIPO":"visitante"},{"NOMBRE":"CRISTHIAN VINICIUS","LICENCIA":"20","DORSAL":"7","CODPARTICIPANTE":"39738138","FECHA_NACIMIENTO":2,"PORTERO":null,"TIPO":"normal","MINUTO":"50","EQUIPO":"visitante"},{"NOMBRE":"TIDIAN","LICENCIA":"20","DORSAL":"9","CODPARTICIPANTE":"39776707","FECHA_NACIMIENTO":2,"PORTERO":null,"TIPO":"normal","MINUTO":"44","EQUIPO":"visitante"},{"NOMBRE":"ELVIS GERARD","LICENCIA":"20","DORSAL":"10","CODPARTICIPANTE":"33204713","FECHA_NACIMIENTO":2,"PORTERO":null,"TIPO":"normal","MINUTO":"55","EQUIPO":"local"}],"EQUIPO_CASA":{"CODCLUB":1084,"CODCLUB2":1084,"CODEQUIPO":33934,"NOMBRE_CLUB":"MONTAÑESA, C.F.","NOMBRE_CLUB_URL":"montanesa-cf","NOMBRE_EQUIPO":"MONTAÑESA, C.F. D","NOMBRE_EQUIPO_URL":"montanesa-cf-d","NOMBRE":"00100_0000584781_montanesa_200x200.png","NOMBRE_ABREVIADO_URL":"3al","CODGRUPO":42203031,"TITULARES":[{"NOMBRE":"IKER","LICENCIA":"20","DORSAL":"3","CODPARTICIPANTE":"36667810","FECHA_NACIMIENTO":2,"PORTERO":null},{"NOMBRE":"FCO JAVIER","LICENCIA":"20","DORSAL":"4","CODPARTICIPANTE":"45478660","FECHA_NACIMIENTO":1,"PORTERO":null},{"NOMBRE":"EROS","LICENCIA":"20","DORSAL":"7","CODPARTICIPANTE":"41599922","FECHA_NACIMIENTO":2,"PORTERO":null},{"NOMBRE":"OSCAR DAVID","LICENCIA":"20","DORSAL":"8","CODPARTICIPANTE":"45481463","FECHA_NACIMIENTO":1,"PORTERO":null},{"NOMBRE":"ELVIS GERARD","LICENCIA":"20","DORSAL":"10","CODPARTICIPANTE":"33204713","FECHA_NACIMIENTO":2,"PORTERO":null},{"NOMBRE":"GIOVANNY","LICENCIA":"20","DORSAL":"11","CODPARTICIPANTE":"39358523","FECHA_NACIMIENTO":1,"PORTERO":null},{"NOMBRE":"IVAN","LICENCIA":"20","DORSAL":"99","CODPARTICIPANTE":"45480224","FECHA_NACIMIENTO":1,"PORTERO":1}],"SUPLENTES":[{"NOMBRE":"TERRY LIONEL","LICENCIA":"20","DORSAL":"6","CODPARTICIPANTE":"36127118","FECHA_NACIMIENTO":2,"PORTERO":null},{"NOMBRE":"ADAM","LICENCIA":"20","DORSAL":"12","CODPARTICIPANTE":"45479706","FECHA_NACIMIENTO":2,"PORTERO":null},{"NOMBRE":"NOAH","LICENCIA":"20","DORSAL":"14","CODPARTICIPANTE":"32382484","FECHA_NACIMIENTO":2,"PORTERO":null},{"NOMBRE":"JOSUÉ DAVID","LICENCIA":"20","DORSAL":"15","CODPARTICIPANTE":"38327027","FECHA_NACIMIENTO":1,"PORTERO":null},{"NOMBRE":"MARC","LICENCIA":"20","DORSAL":"16","CODPARTICIPANTE":"43219194","FECHA_NACIMIENTO":2,"PORTERO":null},{"NOMBRE":"YOUSEF","LICENCIA":"20","DORSAL":"17","CODPARTICIPANTE":"42458438","FECHA_NACIMIENTO":2,"PORTERO":null}],"COSTECNIC":{"":"ANTONIO"},"SUSTITUCIONES":[],"SANCIONES":[{"NOMBRE":"TERRY LIONEL","LICENCIA":"20","DORSAL":"6","CODPARTICIPANTE":"36127118","FECHA_NACIMIENTO":2,"PORTERO":null,"TIPO":"groga","MINUTO":"43"}]},"EQUIPO_FUERA":{"CODCLUB":2930,"CODCLUB2":2930,"CODEQUIPO":32324228,"NOMBRE_CLUB":"Pª BARC. CINC COPES","NOMBRE_CLUB_URL":"pa-barc-cinc-copes","NOMBRE_EQUIPO":"Pª BARC. CINC COPES H","NOMBRE_EQUIPO_URL":"pa-barc-cinc-copes-h","NOMBRE":"00100_0000576648_cinccopes_200x200.png","NOMBRE_ABREVIADO_URL":"3al","CODGRUPO":42204817,"TITULARES":[{"NOMBRE":"LUCAS","LICENCIA":"20","DORSAL":"1","CODPARTICIPANTE":"33814597","FECHA_NACIMIENTO":2,"PORTERO":1},{"NOMBRE":"BERNAT","LICENCIA":"20","DORSAL":"3","CODPARTICIPANTE":"33826069","FECHA_NACIMIENTO":2,"PORTERO":null},{"NOMBRE":"PAU","LICENCIA":"20","DORSAL":"5","CODPARTICIPANTE":"33987702","FECHA_NACIMIENTO":2,"PORTERO":null},{"NOMBRE":"NICOLAS","LICENCIA":"20","DORSAL":"8","CODPARTICIPANTE":"33815731","FECHA_NACIMIENTO":2,"PORTERO":null},{"NOMBRE":"TIDIAN","LICENCIA":"20","DORSAL":"9","CODPARTICIPANTE":"39776707","FECHA_NACIMIENTO":2,"PORTERO":null},{"NOMBRE":"ARAN","LICENCIA":"20","DORSAL":"10","CODPARTICIPANTE":"42001099","FECHA_NACIMIENTO":2,"PORTERO":null},{"NOMBRE":"POL","LICENCIA":"20","DORSAL":"60","CODPARTICIPANTE":"43684972","FECHA_NACIMIENTO":2,"PORTERO":null}],"SUPLENTES":[{"NOMBRE":"AITOR","LICENCIA":"20","DORSAL":"2","CODPARTICIPANTE":"39808118","FECHA_NACIMIENTO":2,"PORTERO":null},{"NOMBRE":"CRISTHIAN VINICIUS","LICENCIA":"20","DORSAL":"7","CODPARTICIPANTE":"39738138","FECHA_NACIMIENTO":2,"PORTERO":null},{"NOMBRE":"JUAN ANTONIO","LICENCIA":"20","DORSAL":"11","CODPARTICIPANTE":"33032377","FECHA_NACIMIENTO":2,"PORTERO":null}],"COSTECNIC":{"Entrenador Titular":"ÀLEX"},"SUSTITUCIONES":[],"SANCIONES":[]}},"codacta":"3082718","titulars_local":[{"codparticipant":36667810,"codequip":33934,"dorsal":3,"titularitats":1,"porter":null,"nom":"IKER","any":2012,"partits":1,"nom_equip":"MONTAÑESA, C.F. D","colorequipacio1":"#FFFF00","colorequipacio2":"#FF70D9"},{"codparticipant":45478660,"codequip":33934,"dorsal":4,"titularitats":1,"porter":null,"nom":"FCO JAVIER","any":2011,"partits":1,"nom_equip":"MONTAÑESA, C.F. D","colorequipacio1":"#FFFF00","colorequipacio2":"#FF70D9"},{"codparticipant":36127118,"codequip":33934,"dorsal":6,"titularitats":0,"porter":null,"nom":"TERRY LIONEL","any":2012,"partits":1,"nom_equip":"MONTAÑESA, C.F. D","colorequipacio1":"#FFFF00","colorequipacio2":"#FF70D9"},{"codparticipant":41599922,"codequip":33934,"dorsal":7,"titularitats":1,"porter":null,"nom":"EROS","any":2012,"partits":1,"nom_equip":"MONTAÑESA, C.F. D","colorequipacio1":"#FFFF00","colorequipacio2":"#FF70D9"},{"codparticipant":45481463,"codequip":33934,"dorsal":8,"titularitats":1,"porter":null,"nom":"OSCAR DAVID","any":2011,"partits":1,"nom_equip":"MONTAÑESA, C.F. D","colorequipacio1":"#FFFF00","colorequipacio2":"#FF70D9"},{"codparticipant":33204713,"codequip":33934,"dorsal":10,"titularitats":1,"porter":null,"nom":"ELVIS GERARD","any":2012,"partits":1,"nom_equip":"MONTAÑESA, C.F. D","colorequipacio1":"#FFFF00","colorequipacio2":"#FF70D9"},{"codparticipant":39358523,"codequip":33934,"dorsal":11,"titularitats":1,"porter":null,"nom":"GIOVANNY","any":2011,"partits":1,"nom_equip":"MONTAÑESA, C.F. D","colorequipacio1":"#FFFF00","colorequipacio2":"#FF70D9"},{"codparticipant":45479706,"codequip":33934,"dorsal":12,"titularitats":0,"porter":null,"nom":"ADAM","any":2012,"partits":1,"nom_equip":"MONTAÑESA, C.F. D","colorequipacio1":"#FFFF00","colorequipacio2":"#FF70D9"},{"codparticipant":32382484,"codequip":33934,"dorsal":14,"titularitats":0,"porter":null,"nom":"NOAH","any":2012,"partits":1,"nom_equip":"MONTAÑESA, C.F. D","colorequipacio1":"#FFFF00","colorequipacio2":"#FF70D9"},{"codparticipant":38327027,"codequip":33934,"dorsal":15,"titularitats":0,"porter":null,"nom":"JOSUÉ DAVID","any":2011,"partits":1,"nom_equip":"MONTAÑESA, C.F. D","colorequipacio1":"#FFFF00","colorequipacio2":"#FF70D9"},{"codparticipant":43219194,"codequip":33934,"dorsal":16,"titularitats":0,"porter":null,"nom":"MARC","any":2012,"partits":1,"nom_equip":"MONTAÑESA, C.F. D","colorequipacio1":"#FFFF00","colorequipacio2":"#FF70D9"},{"codparticipant":42458438,"codequip":33934,"dorsal":17,"titularitats":0,"porter":null,"nom":"YOUSEF","any":2012,"partits":1,"nom_equip":"MONTAÑESA, C.F. D","colorequipacio1":"#FFFF00","colorequipacio2":"#FF70D9"},{"codparticipant":45480224,"codequip":33934,"dorsal":99,"titularitats":1,"porter":1,"nom":"IVAN","any":2011,"partits":1,"nom_equip":"MONTAÑESA, C.F. D","colorequipacio1":"#FFFF00","colorequipacio2":"#FF70D9"}],"titulars_visitant":[{"codparticipant":33814597,"codequip":32324228,"dorsal":1,"titularitats":1,"porter":1,"nom":"LUCAS","any":2012,"partits":1,"nom_equip":"Pª BARC. CINC COPES H","colorequipacio1":"#0000FF","colorequipacio2":"#FFFF00"},{"codparticipant":39808118,"codequip":32324228,"dorsal":2,"titularitats":0,"porter":null,"nom":"AITOR","any":2012,"partits":1,"nom_equip":"Pª BARC. CINC COPES H","colorequipacio1":"#0000FF","colorequipacio2":"#FFFF00"},{"codparticipant":33826069,"codequip":32324228,"dorsal":3,"titularitats":1,"porter":null,"nom":"BERNAT","any":2012,"partits":1,"nom_equip":"Pª BARC. CINC COPES H","colorequipacio1":"#0000FF","colorequipacio2":"#FFFF00"},{"codparticipant":33987702,"codequip":32324228,"dorsal":5,"titularitats":1,"porter":null,"nom":"PAU","any":2012,"partits":1,"nom_equip":"Pª BARC. CINC COPES H","colorequipacio1":"#0000FF","colorequipacio2":"#FFFF00"},{"codparticipant":39738138,"codequip":32324228,"dorsal":7,"titularitats":0,"porter":null,"nom":"CRISTHIAN VINICIUS","any":2012,"partits":1,"nom_equip":"Pª BARC. CINC COPES H","colorequipacio1":"#0000FF","colorequipacio2":"#FFFF00"},{"codparticipant":33815731,"codequip":32324228,"dorsal":8,"titularitats":1,"porter":null,"nom":"NICOLAS","any":2012,"partits":1,"nom_equip":"Pª BARC. CINC COPES H","colorequipacio1":"#0000FF","colorequipacio2":"#FFFF00"},{"codparticipant":39776707,"codequip":32324228,"dorsal":9,"titularitats":1,"porter":null,"nom":"TIDIAN","any":2012,"partits":1,"nom_equip":"Pª BARC. CINC COPES H","colorequipacio1":"#0000FF","colorequipacio2":"#FFFF00"},{"codparticipant":42001099,"codequip":32324228,"dorsal":10,"titularitats":1,"porter":null,"nom":"ARAN","any":2012,"partits":1,"nom_equip":"Pª BARC. CINC COPES H","colorequipacio1":"#0000FF","colorequipacio2":"#FFFF00"},{"codparticipant":33032377,"codequip":32324228,"dorsal":11,"titularitats":0,"porter":null,"nom":"JUAN ANTONIO","any":2012,"partits":1,"nom_equip":"Pª BARC. CINC COPES H","colorequipacio1":"#0000FF","colorequipacio2":"#FFFF00"},{"codparticipant":43684972,"codequip":32324228,"dorsal":60,"titularitats":1,"porter":null,"nom":"POL","any":2012,"partits":1,"nom_equip":"Pª BARC. CINC COPES H","colorequipacio1":"#0000FF","colorequipacio2":"#FFFF00"}],"menuFollowTeams":[{"label":"Aleví A","href":"/classificacio?id=44763989"},{"label":"Aleví B","href":"/classificacio?id=45021968"},{"label":"Aleví C","href":"/classificacio?id=45021534"},{"label":"Aleví D","href":"/classificacio?id=45326344"},{"label":"Aleví E","href":"/classificacio?id=45330942"}]}