{"data":{"INFO":{"CODGRUPO":"45326344","GOLES_CASA":"10","GOLES_FUERA":"0","PENALTIS_CASA":null,"PENALTIS_FUERA":null,"CODACTA":"3082914","COD_COMPETICION":43990569,"NOM_COMPETICION":"ALEVÍ TERCERA DIVISIÓ","NOM_COMPETICION_URL":"alevi-tercera-divisio","COD_GRUPO":45326344,"GRUPO":"GRUP 7","GRUPO_URL":"grup-7","CODEQUIPO_CASA":"43974946","CODEQUIPO_FUERA":"32324228","JORNADA":"28","CODIGO_CAMPO":"1714","COMIENZO1":"2023-05-21 12:00:00","SUSPENDIDO":"0","NOMBRE":"CAMP DE FUTBOL SCHOOL AGORA INTERNATIONAL SANT CUGAT","DIRECCION":"c/ Ferrer i Guàrdia, s/n","TEMP_NOMBRE":"2223","TEMP_LARGO":"TEMPORADA 2022-2023","CIUDAD":"Sant Cugat Del Vallès","ESTADO":"4"},"ARBITROS":[{"CODTIPO_ARBITRO":"1","CODARBITRO":"3168979","NOMBRE_ARBITRO":"ARNAU","NOMBRE":"Vallès Occidental"}],"GOLES":[{"NOMBRE":"JAUME","LICENCIA":"20","DORSAL":"5","CODPARTICIPANTE":"37174569","FECHA_NACIMIENTO":2,"PORTERO":null,"TIPO":"normal","MINUTO":"49","EQUIPO":"local"},{"NOMBRE":"JAVIER","LICENCIA":"12","DORSAL":"6","CODPARTICIPANTE":"45672730","FECHA_NACIMIENTO":1,"PORTERO":1,"TIPO":"normal","MINUTO":"35","EQUIPO":"local"},{"NOMBRE":"JAVIER","LICENCIA":"12","DORSAL":"6","CODPARTICIPANTE":"45672730","FECHA_NACIMIENTO":1,"PORTERO":1,"TIPO":"normal","MINUTO":"48","EQUIPO":"local"},{"NOMBRE":"MATTEO","LICENCIA":"20","DORSAL":"10","CODPARTICIPANTE":"46016982","FECHA_NACIMIENTO":1,"PORTERO":null,"TIPO":"normal","MINUTO":"16","EQUIPO":"local"},{"NOMBRE":"MATTEO","LICENCIA":"20","DORSAL":"10","CODPARTICIPANTE":"46016982","FECHA_NACIMIENTO":1,"PORTERO":null,"TIPO":"normal","MINUTO":"21","EQUIPO":"local"},{"NOMBRE":"MATTEO","LICENCIA":"20","DORSAL":"10","CODPARTICIPANTE":"46016982","FECHA_NACIMIENTO":1,"PORTERO":null,"TIPO":"normal","MINUTO":"27","EQUIPO":"local"},{"NOMBRE":"EDGAR","LICENCIA":"20","DORSAL":"14","CODPARTICIPANTE":"45944113","FECHA_NACIMIENTO":2,"PORTERO":null,"TIPO":"normal","MINUTO":"8","EQUIPO":"local"},{"NOMBRE":"EDGAR","LICENCIA":"20","DORSAL":"14","CODPARTICIPANTE":"45944113","FECHA_NACIMIENTO":2,"PORTERO":null,"TIPO":"normal","MINUTO":"10","EQUIPO":"local"},{"NOMBRE":"EDGAR","LICENCIA":"20","DORSAL":"14","CODPARTICIPANTE":"45944113","FECHA_NACIMIENTO":2,"PORTERO":null,"TIPO":"normal","MINUTO":"31","EQUIPO":"local"},{"NOMBRE":"NUNO","LICENCIA":"20","DORSAL":"17","CODPARTICIPANTE":"41151758","FECHA_NACIMIENTO":2,"PORTERO":null,"TIPO":"normal","MINUTO":"2","EQUIPO":"local"},{"NOMBRE":"NUNO","LICENCIA":"20","DORSAL":"17","CODPARTICIPANTE":"41151758","FECHA_NACIMIENTO":2,"PORTERO":null,"TIPO":"normal","MINUTO":"19","EQUIPO":"local"},{"NOMBRE":"ESTEBAN","LICENCIA":"20","DORSAL":"20","CODPARTICIPANTE":"46070796","FECHA_NACIMIENTO":2,"PORTERO":null,"TIPO":"normal","MINUTO":"23","EQUIPO":"local"},{"NOMBRE":"ESTEBAN","LICENCIA":"20","DORSAL":"20","CODPARTICIPANTE":"46070796","FECHA_NACIMIENTO":2,"PORTERO":null,"TIPO":"normal","MINUTO":"26","EQUIPO":"local"},{"NOMBRE":"ESTEBAN","LICENCIA":"20","DORSAL":"20","CODPARTICIPANTE":"46070796","FECHA_NACIMIENTO":2,"PORTERO":null,"TIPO":"normal","MINUTO":"58","EQUIPO":"local"}],"EQUIPO_CASA":{"CODCLUB":6612,"CODCLUB2":43918619,"CODEQUIPO":43974946,"NOMBRE_CLUB":"VALLDOREIX, F.C.","NOMBRE_CLUB_URL":"valldoreix-fc","NOMBRE_EQUIPO":"VALLDOREIX, F.C. A","NOMBRE_EQUIPO_URL":"valldoreix-fc-a","NOMBRE":"00100_0000878137_valldoreixfc_200.png","NOMBRE_ABREVIADO_URL":"3al","CODGRUPO":45326344,"TITULARES":[{"NOMBRE":"JAUME","LICENCIA":"20","DORSAL":"5","CODPARTICIPANTE":"37174569","FECHA_NACIMIENTO":2,"PORTERO":null},{"NOMBRE":"JAVIER","LICENCIA":"12","DORSAL":"6","CODPARTICIPANTE":"45672730","FECHA_NACIMIENTO":1,"PORTERO":1},{"NOMBRE":"MATTEO","LICENCIA":"20","DORSAL":"10","CODPARTICIPANTE":"46016982","FECHA_NACIMIENTO":1,"PORTERO":null},{"NOMBRE":"TOMAS","LICENCIA":"20","DORSAL":"11","CODPARTICIPANTE":"45993588","FECHA_NACIMIENTO":1,"PORTERO":null},{"NOMBRE":"EDGAR","LICENCIA":"20","DORSAL":"14","CODPARTICIPANTE":"45944113","FECHA_NACIMIENTO":2,"PORTERO":null},{"NOMBRE":"NUNO","LICENCIA":"20","DORSAL":"17","CODPARTICIPANTE":"41151758","FECHA_NACIMIENTO":2,"PORTERO":null},{"NOMBRE":"ESTEBAN","LICENCIA":"20","DORSAL":"20","CODPARTICIPANTE":"46070796","FECHA_NACIMIENTO":2,"PORTERO":null}],"SUPLENTES":[],"COSTECNIC":{"Delegat":"JAVIER","Entrenador Titular":"JAVIER"},"SUSTITUCIONES":[],"SANCIONES":[]},"EQUIPO_FUERA":{"CODCLUB":2930,"CODCLUB2":2930,"CODEQUIPO":32324228,"NOMBRE_CLUB":"Pª BARC. CINC COPES","NOMBRE_CLUB_URL":"pa-barc-cinc-copes","NOMBRE_EQUIPO":"Pª BARC. CINC COPES H","NOMBRE_EQUIPO_URL":"pa-barc-cinc-copes-h","NOMBRE":"00100_0000576648_cinccopes_200x200.png","NOMBRE_ABREVIADO_URL":"3al","CODGRUPO":42204817,"TITULARES":[{"NOMBRE":"LUCAS","LICENCIA":"20","DORSAL":"1","CODPARTICIPANTE":"33814597","FECHA_NACIMIENTO":2,"PORTERO":1},{"NOMBRE":"PAU","LICENCIA":"20","DORSAL":"5","CODPARTICIPANTE":"33987702","FECHA_NACIMIENTO":2,"PORTERO":null},{"NOMBRE":"POL","LICENCIA":"20","DORSAL":"6","CODPARTICIPANTE":"43684972","FECHA_NACIMIENTO":2,"PORTERO":null},{"NOMBRE":"CRISTHIAN VINICIUS","LICENCIA":"20","DORSAL":"7","CODPARTICIPANTE":"39738138","FECHA_NACIMIENTO":2,"PORTERO":null},{"NOMBRE":"NICOLAS","LICENCIA":"20","DORSAL":"8","CODPARTICIPANTE":"33815731","FECHA_NACIMIENTO":2,"PORTERO":null},{"NOMBRE":"TIDIAN","LICENCIA":"20","DORSAL":"9","CODPARTICIPANTE":"39776707","FECHA_NACIMIENTO":2,"PORTERO":null},{"NOMBRE":"ARAN","LICENCIA":"20","DORSAL":"10","CODPARTICIPANTE":"42001099","FECHA_NACIMIENTO":2,"PORTERO":null}],"SUPLENTES":[],"COSTECNIC":{"Entrenador Titular":"YAGO"},"SUSTITUCIONES":[],"SANCIONES":[]}},"codacta":"3082914","titulars_local":[{"codparticipant":37174569,"codequip":43974946,"dorsal":5,"titularitats":1,"porter":null,"nom":"JAUME","any":2012,"partits":1,"nom_equip":"VALLDOREIX, F.C. A","colorequipacio1":"#648B34","colorequipacio2":"#222222"},{"codparticipant":45672730,"codequip":43974946,"dorsal":6,"titularitats":1,"porter":1,"nom":"JAVIER","any":2011,"partits":1,"nom_equip":"VALLDOREIX, F.C. A","colorequipacio1":"#648B34","colorequipacio2":"#222222"},{"codparticipant":46016982,"codequip":43974946,"dorsal":10,"titularitats":1,"porter":null,"nom":"MATTEO","any":2011,"partits":1,"nom_equip":"VALLDOREIX, F.C. A","colorequipacio1":"#648B34","colorequipacio2":"#222222"},{"codparticipant":45993588,"codequip":43974946,"dorsal":11,"titularitats":1,"porter":null,"nom":"TOMAS","any":2011,"partits":1,"nom_equip":"VALLDOREIX, F.C. A","colorequipacio1":"#648B34","colorequipacio2":"#222222"},{"codparticipant":45944113,"codequip":43974946,"dorsal":14,"titularitats":1,"porter":null,"nom":"EDGAR","any":2012,"partits":1,"nom_equip":"VALLDOREIX, F.C. A","colorequipacio1":"#648B34","colorequipacio2":"#222222"},{"codparticipant":41151758,"codequip":43974946,"dorsal":17,"titularitats":1,"porter":null,"nom":"NUNO","any":2012,"partits":1,"nom_equip":"VALLDOREIX, F.C. A","colorequipacio1":"#648B34","colorequipacio2":"#222222"},{"codparticipant":46070796,"codequip":43974946,"dorsal":20,"titularitats":1,"porter":null,"nom":"ESTEBAN","any":2012,"partits":1,"nom_equip":"VALLDOREIX, F.C. A","colorequipacio1":"#648B34","colorequipacio2":"#222222"}],"titulars_visitant":[{"codparticipant":33814597,"codequip":32324228,"dorsal":1,"titularitats":1,"porter":1,"nom":"LUCAS","any":2012,"partits":1,"nom_equip":"Pª BARC. CINC COPES H","colorequipacio1":"#0000FF","colorequipacio2":"#FFFF00"},{"codparticipant":33987702,"codequip":32324228,"dorsal":5,"titularitats":1,"porter":null,"nom":"PAU","any":2012,"partits":1,"nom_equip":"Pª BARC. CINC COPES H","colorequipacio1":"#0000FF","colorequipacio2":"#FFFF00"},{"codparticipant":43684972,"codequip":32324228,"dorsal":6,"titularitats":1,"porter":null,"nom":"POL","any":2012,"partits":1,"nom_equip":"Pª BARC. CINC COPES H","colorequipacio1":"#0000FF","colorequipacio2":"#FFFF00"},{"codparticipant":39738138,"codequip":32324228,"dorsal":7,"titularitats":1,"porter":null,"nom":"CRISTHIAN VINICIUS","any":2012,"partits":1,"nom_equip":"Pª BARC. CINC COPES H","colorequipacio1":"#0000FF","colorequipacio2":"#FFFF00"},{"codparticipant":33815731,"codequip":32324228,"dorsal":8,"titularitats":1,"porter":null,"nom":"NICOLAS","any":2012,"partits":1,"nom_equip":"Pª BARC. CINC COPES H","colorequipacio1":"#0000FF","colorequipacio2":"#FFFF00"},{"codparticipant":39776707,"codequip":32324228,"dorsal":9,"titularitats":1,"porter":null,"nom":"TIDIAN","any":2012,"partits":1,"nom_equip":"Pª BARC. CINC COPES H","colorequipacio1":"#0000FF","colorequipacio2":"#FFFF00"},{"codparticipant":42001099,"codequip":32324228,"dorsal":10,"titularitats":1,"porter":null,"nom":"ARAN","any":2012,"partits":1,"nom_equip":"Pª BARC. CINC COPES H","colorequipacio1":"#0000FF","colorequipacio2":"#FFFF00"}],"menuFollowTeams":[{"label":"Aleví A","href":"/classificacio?id=44763989"},{"label":"Aleví B","href":"/classificacio?id=45021968"},{"label":"Aleví C","href":"/classificacio?id=45021534"},{"label":"Aleví D","href":"/classificacio?id=45326344"},{"label":"Aleví E","href":"/classificacio?id=45330942"}]}