{"data":{"INFO":{"CODGRUPO":"45330942","GOLES_CASA":"0","GOLES_FUERA":"4","PENALTIS_CASA":null,"PENALTIS_FUERA":null,"CODACTA":"3086549","COD_COMPETICION":43990569,"NOM_COMPETICION":"ALEVÍ TERCERA DIVISIÓ","NOM_COMPETICION_URL":"alevi-tercera-divisio","COD_GRUPO":45330942,"GRUPO":"GRUP 13","GRUPO_URL":"grup-13","CODEQUIPO_CASA":"40880","CODEQUIPO_FUERA":"41271222","JORNADA":"23","CODIGO_CAMPO":"310","COMIENZO1":"2023-04-16 12:35:00","SUSPENDIDO":"0","NOMBRE":"CAMP DE FUTBOL CEM CLOT DE LA MEL","DIRECCION":"c/ d'Andrade, 40","TEMP_NOMBRE":"2223","TEMP_LARGO":"TEMPORADA 2022-2023","CIUDAD":"Barcelona","ESTADO":"4"},"ARBITROS":[{"CODTIPO_ARBITRO":"1","CODARBITRO":"3388543","NOMBRE_ARBITRO":"DANIEL","NOMBRE":"Barcelona3"}],"GOLES":[{"NOMBRE":"STEVEN","LICENCIA":"20","DORSAL":"3","CODPARTICIPANTE":"45942317","FECHA_NACIMIENTO":1,"PORTERO":null,"TIPO":"normal","MINUTO":"35","EQUIPO":"visitante"},{"NOMBRE":"ALEXANDER","LICENCIA":"20","DORSAL":"6","CODPARTICIPANTE":"42624524","FECHA_NACIMIENTO":2,"PORTERO":null,"TIPO":"normal","MINUTO":"5","EQUIPO":"visitante"},{"NOMBRE":"LUKA","LICENCIA":"20","DORSAL":"7","CODPARTICIPANTE":"38819250","FECHA_NACIMIENTO":2,"PORTERO":null,"TIPO":"normal","MINUTO":"25","EQUIPO":"visitante"},{"NOMBRE":"MOHAMED ROCHDY","LICENCIA":"20","DORSAL":"9","CODPARTICIPANTE":"43579246","FECHA_NACIMIENTO":2,"PORTERO":null,"TIPO":"normal","MINUTO":"49","EQUIPO":"visitante"}],"EQUIPO_CASA":{"CODCLUB":6237,"CODCLUB2":6237,"CODEQUIPO":40880,"NOMBRE_CLUB":"VILA OLIMPICA CLUB ESPORTIU","NOMBRE_CLUB_URL":"vila-olimpica-club-esportiu","NOMBRE_EQUIPO":"VILA OLIMPICA CLUB ESP. E","NOMBRE_EQUIPO_URL":"vila-olimpica-club-esp-e","NOMBRE":"00100_0000586311_cevo_200x200.png","NOMBRE_ABREVIADO_URL":"3al","CODGRUPO":41527092,"TITULARES":[{"NOMBRE":"DIEGO","LICENCIA":"20","DORSAL":"1","CODPARTICIPANTE":"45890410","FECHA_NACIMIENTO":2,"PORTERO":1},{"NOMBRE":"LUCAS","LICENCIA":"20","DORSAL":"10","CODPARTICIPANTE":"38488906","FECHA_NACIMIENTO":2,"PORTERO":null},{"NOMBRE":"JESUS","LICENCIA":"20","DORSAL":"22","CODPARTICIPANTE":"33908116","FECHA_NACIMIENTO":2,"PORTERO":null},{"NOMBRE":"DEREK","LICENCIA":"20","DORSAL":"23","CODPARTICIPANTE":"37174866","FECHA_NACIMIENTO":2,"PORTERO":null},{"NOMBRE":"YOJAN","LICENCIA":"20","DORSAL":"43","CODPARTICIPANTE":"30989192","FECHA_NACIMIENTO":2,"PORTERO":null},{"NOMBRE":"MOISES","LICENCIA":"20","DORSAL":"50","CODPARTICIPANTE":"33207719","FECHA_NACIMIENTO":2,"PORTERO":null},{"NOMBRE":"JOEL","LICENCIA":"20","DORSAL":"57","CODPARTICIPANTE":"36003734","FECHA_NACIMIENTO":2,"PORTERO":null}],"SUPLENTES":[{"NOMBRE":"JAN","LICENCIA":"20","DORSAL":"40","CODPARTICIPANTE":"41361424","FECHA_NACIMIENTO":2,"PORTERO":null}],"COSTECNIC":{"Delegat":"JOAN","Entrenador Titular":"POL"},"SUSTITUCIONES":[],"SANCIONES":[]},"EQUIPO_FUERA":{"CODCLUB":6592,"CODCLUB2":40492704,"CODEQUIPO":41271222,"NOMBRE_CLUB":"FUNDACIÓ ACADEMIA F. L\\'HOSPITALET ","NOMBRE_CLUB_URL":"fundacio-academia-f-lhospitalet","NOMBRE_EQUIPO":"FUNDACIÓ ACADÈMIA F. L\\'HOSPITALET  D","NOMBRE_EQUIPO_URL":"fundacio-academia-f-lhospitalet-d","NOMBRE":"00100_0000817600_faf_200.png","NOMBRE_ABREVIADO_URL":"3al","CODGRUPO":42202103,"TITULARES":[{"NOMBRE":"RIZWAN AHMED","LICENCIA":"20","DORSAL":"1","CODPARTICIPANTE":"42574555","FECHA_NACIMIENTO":2,"PORTERO":1},{"NOMBRE":"STEVEN","LICENCIA":"20","DORSAL":"3","CODPARTICIPANTE":"45942317","FECHA_NACIMIENTO":1,"PORTERO":null},{"NOMBRE":"JOSE DAVID","LICENCIA":"20","DORSAL":"4","CODPARTICIPANTE":"37132784","FECHA_NACIMIENTO":2,"PORTERO":null},{"NOMBRE":"BERNAT JOSEP","LICENCIA":"20","DORSAL":"5","CODPARTICIPANTE":"42625841","FECHA_NACIMIENTO":2,"PORTERO":null},{"NOMBRE":"ALEXANDER","LICENCIA":"20","DORSAL":"6","CODPARTICIPANTE":"42624524","FECHA_NACIMIENTO":2,"PORTERO":null},{"NOMBRE":"LUKA","LICENCIA":"20","DORSAL":"7","CODPARTICIPANTE":"38819250","FECHA_NACIMIENTO":2,"PORTERO":null},{"NOMBRE":"MOHAMED ROCHDY","LICENCIA":"20","DORSAL":"9","CODPARTICIPANTE":"43579246","FECHA_NACIMIENTO":2,"PORTERO":null}],"SUPLENTES":[{"NOMBRE":"YAGO","LICENCIA":"12","DORSAL":"8","CODPARTICIPANTE":"39376937","FECHA_NACIMIENTO":1,"PORTERO":null},{"NOMBRE":"AIDEN","LICENCIA":"20","DORSAL":"10","CODPARTICIPANTE":"37217790","FECHA_NACIMIENTO":2,"PORTERO":null}],"COSTECNIC":{"Entrenador Titular":"MARC"},"SUSTITUCIONES":[],"SANCIONES":[{"NOMBRE":"BERNAT JOSEP","LICENCIA":"20","DORSAL":"5","CODPARTICIPANTE":"42625841","FECHA_NACIMIENTO":2,"PORTERO":null,"TIPO":"groga","MINUTO":"28"},{"NOMBRE":"ALEXANDER","LICENCIA":"20","DORSAL":"6","CODPARTICIPANTE":"42624524","FECHA_NACIMIENTO":2,"PORTERO":null,"TIPO":"groga","MINUTO":"55"}]}},"codacta":"3086549","titulars_local":[{"codparticipant":45890410,"codequip":40880,"dorsal":1,"titularitats":1,"porter":1,"nom":"DIEGO","any":2012,"partits":1,"nom_equip":"VILA OLIMPICA CLUB ESP. E","colorequipacio1":"#2148D9","colorequipacio2":"#FFFF06"},{"codparticipant":38488906,"codequip":40880,"dorsal":10,"titularitats":1,"porter":null,"nom":"LUCAS","any":2012,"partits":1,"nom_equip":"VILA OLIMPICA CLUB ESP. E","colorequipacio1":"#2148D9","colorequipacio2":"#FFFF06"},{"codparticipant":33908116,"codequip":40880,"dorsal":22,"titularitats":1,"porter":null,"nom":"JESUS","any":2012,"partits":1,"nom_equip":"VILA OLIMPICA CLUB ESP. E","colorequipacio1":"#2148D9","colorequipacio2":"#FFFF06"},{"codparticipant":37174866,"codequip":40880,"dorsal":23,"titularitats":1,"porter":null,"nom":"DEREK","any":2012,"partits":1,"nom_equip":"VILA OLIMPICA CLUB ESP. E","colorequipacio1":"#2148D9","colorequipacio2":"#FFFF06"},{"codparticipant":41361424,"codequip":40880,"dorsal":40,"titularitats":0,"porter":null,"nom":"JAN","any":2012,"partits":1,"nom_equip":"VILA OLIMPICA CLUB ESP. E","colorequipacio1":"#2148D9","colorequipacio2":"#FFFF06"},{"codparticipant":30989192,"codequip":40880,"dorsal":43,"titularitats":1,"porter":null,"nom":"YOJAN","any":2012,"partits":1,"nom_equip":"VILA OLIMPICA CLUB ESP. E","colorequipacio1":"#2148D9","colorequipacio2":"#FFFF06"},{"codparticipant":33207719,"codequip":40880,"dorsal":50,"titularitats":1,"porter":null,"nom":"MOISES","any":2012,"partits":1,"nom_equip":"VILA OLIMPICA CLUB ESP. E","colorequipacio1":"#2148D9","colorequipacio2":"#FFFF06"},{"codparticipant":36003734,"codequip":40880,"dorsal":57,"titularitats":1,"porter":null,"nom":"JOEL","any":2012,"partits":1,"nom_equip":"VILA OLIMPICA CLUB ESP. E","colorequipacio1":"#2148D9","colorequipacio2":"#FFFF06"}],"titulars_visitant":[{"codparticipant":42574555,"codequip":41271222,"dorsal":1,"titularitats":1,"porter":1,"nom":"RIZWAN AHMED","any":2012,"partits":1,"nom_equip":"FUNDACIÓ ACADÈMIA F. L\\'HOSPITALET  D","colorequipacio1":"#222222","colorequipacio2":"#FF7AA0"},{"codparticipant":45942317,"codequip":41271222,"dorsal":3,"titularitats":1,"porter":null,"nom":"STEVEN","any":2011,"partits":1,"nom_equip":"FUNDACIÓ ACADÈMIA F. L\\'HOSPITALET  D","colorequipacio1":"#222222","colorequipacio2":"#FF7AA0"},{"codparticipant":37132784,"codequip":41271222,"dorsal":4,"titularitats":1,"porter":null,"nom":"JOSE DAVID","any":2012,"partits":1,"nom_equip":"FUNDACIÓ ACADÈMIA F. L\\'HOSPITALET  D","colorequipacio1":"#222222","colorequipacio2":"#FF7AA0"},{"codparticipant":42625841,"codequip":41271222,"dorsal":5,"titularitats":1,"porter":null,"nom":"BERNAT JOSEP","any":2012,"partits":1,"nom_equip":"FUNDACIÓ ACADÈMIA F. L\\'HOSPITALET  D","colorequipacio1":"#222222","colorequipacio2":"#FF7AA0"},{"codparticipant":42624524,"codequip":41271222,"dorsal":6,"titularitats":1,"porter":null,"nom":"ALEXANDER","any":2012,"partits":1,"nom_equip":"FUNDACIÓ ACADÈMIA F. L\\'HOSPITALET  D","colorequipacio1":"#222222","colorequipacio2":"#FF7AA0"},{"codparticipant":38819250,"codequip":41271222,"dorsal":7,"titularitats":1,"porter":null,"nom":"LUKA","any":2012,"partits":1,"nom_equip":"FUNDACIÓ ACADÈMIA F. L\\'HOSPITALET  D","colorequipacio1":"#222222","colorequipacio2":"#FF7AA0"},{"codparticipant":39376937,"codequip":41271222,"dorsal":8,"titularitats":0,"porter":null,"nom":"YAGO","any":2011,"partits":1,"nom_equip":"FUNDACIÓ ACADÈMIA F. L\\'HOSPITALET  D","colorequipacio1":"#222222","colorequipacio2":"#FF7AA0"},{"codparticipant":43579246,"codequip":41271222,"dorsal":9,"titularitats":1,"porter":null,"nom":"MOHAMED ROCHDY","any":2012,"partits":1,"nom_equip":"FUNDACIÓ ACADÈMIA F. L\\'HOSPITALET  D","colorequipacio1":"#222222","colorequipacio2":"#FF7AA0"},{"codparticipant":37217790,"codequip":41271222,"dorsal":10,"titularitats":0,"porter":null,"nom":"AIDEN","any":2012,"partits":1,"nom_equip":"FUNDACIÓ ACADÈMIA F. L\\'HOSPITALET  D","colorequipacio1":"#222222","colorequipacio2":"#FF7AA0"}],"menuFollowTeams":[{"label":"Aleví A","href":"/classificacio?id=44763989"},{"label":"Aleví B","href":"/classificacio?id=45021968"},{"label":"Aleví C","href":"/classificacio?id=45021534"},{"label":"Aleví D","href":"/classificacio?id=45326344"},{"label":"Aleví E","href":"/classificacio?id=45330942"}]}