{"data":{"INFO":{"CODGRUPO":"45330942","GOLES_CASA":"1","GOLES_FUERA":"4","PENALTIS_CASA":null,"PENALTIS_FUERA":null,"CODACTA":"3086593","COD_COMPETICION":43990569,"NOM_COMPETICION":"ALEVÍ TERCERA DIVISIÓ","NOM_COMPETICION_URL":"alevi-tercera-divisio","COD_GRUPO":45330942,"GRUPO":"GRUP 13","GRUPO_URL":"grup-13","CODEQUIPO_CASA":"32492858","CODEQUIPO_FUERA":"40479","JORNADA":"29","CODIGO_CAMPO":"206","COMIENZO1":"2023-05-27 14:45:00","SUSPENDIDO":"0","NOMBRE":"CAMP DE FUTBOL MPAL. PARC CATALANA","DIRECCION":"c/ del Doctor Aiguader, 58","TEMP_NOMBRE":"2223","TEMP_LARGO":"TEMPORADA 2022-2023","CIUDAD":"Barcelona","ESTADO":"4"},"ARBITROS":[{"CODTIPO_ARBITRO":"1","CODARBITRO":"3389449","NOMBRE_ARBITRO":"FELIX","NOMBRE":"Barcelona3"}],"GOLES":[{"NOMBRE":"ALEX","LICENCIA":"20","DORSAL":"2","CODPARTICIPANTE":"45681603","FECHA_NACIMIENTO":2,"PORTERO":null,"TIPO":"normal","MINUTO":"54","EQUIPO":"visitante"},{"NOMBRE":"ERIC GRABRIEL","LICENCIA":"20","DORSAL":"6","CODPARTICIPANTE":"45434545","FECHA_NACIMIENTO":2,"PORTERO":null,"TIPO":"normal","MINUTO":"56","EQUIPO":"visitante"},{"NOMBRE":"YANZE","LICENCIA":"20","DORSAL":"6","CODPARTICIPANTE":"33821875","FECHA_NACIMIENTO":1,"PORTERO":null,"TIPO":"normal","MINUTO":"4","EQUIPO":"local"},{"NOMBRE":"JAVIER","LICENCIA":"20","DORSAL":"8","CODPARTICIPANTE":"41267611","FECHA_NACIMIENTO":1,"PORTERO":null,"TIPO":"normal","MINUTO":"36","EQUIPO":"visitante"},{"NOMBRE":"JOEN FELIP","LICENCIA":"20","DORSAL":"10","CODPARTICIPANTE":"45436635","FECHA_NACIMIENTO":2,"PORTERO":null,"TIPO":"normal","MINUTO":"58","EQUIPO":"visitante"}],"EQUIPO_CASA":{"CODCLUB":2930,"CODCLUB2":2930,"CODEQUIPO":32492858,"NOMBRE_CLUB":"Pª BARC. CINC COPES","NOMBRE_CLUB_URL":"pa-barc-cinc-copes","NOMBRE_EQUIPO":"Pª BARC. CINC COPES I","NOMBRE_EQUIPO_URL":"pa-barc-cinc-copes-i","NOMBRE":"00100_0000576648_cinccopes_200x200.png","NOMBRE_ABREVIADO_URL":"3al","CODGRUPO":45330942,"TITULARES":[{"NOMBRE":"SAMUEL","LICENCIA":"15213578","DORSAL":"2","CODPARTICIPANTE":"39702568","FECHA_NACIMIENTO":2,"PORTERO":null},{"NOMBRE":"GUILLERMO","LICENCIA":"20","DORSAL":"4","CODPARTICIPANTE":"42839530","FECHA_NACIMIENTO":2,"PORTERO":null},{"NOMBRE":"ARNAU","LICENCIA":"20","DORSAL":"5","CODPARTICIPANTE":"45886400","FECHA_NACIMIENTO":1,"PORTERO":null},{"NOMBRE":"YANZE","LICENCIA":"20","DORSAL":"6","CODPARTICIPANTE":"33821875","FECHA_NACIMIENTO":1,"PORTERO":null},{"NOMBRE":"DYLAN GERARD","LICENCIA":"15213578","DORSAL":"8","CODPARTICIPANTE":"42856711","FECHA_NACIMIENTO":2,"PORTERO":null},{"NOMBRE":"BRUC","LICENCIA":"20","DORSAL":"9","CODPARTICIPANTE":"45956950","FECHA_NACIMIENTO":1,"PORTERO":null},{"NOMBRE":"BERTRAN","LICENCIA":"12","DORSAL":"13","CODPARTICIPANTE":"46739607","FECHA_NACIMIENTO":1,"PORTERO":1}],"SUPLENTES":[{"NOMBRE":"LUIS GONZALO","LICENCIA":"15213578","DORSAL":"10","CODPARTICIPANTE":"46185278","FECHA_NACIMIENTO":2,"PORTERO":null}],"COSTECNIC":{"Entrenador Titular":"MANUEL"},"SUSTITUCIONES":[],"SANCIONES":[]},"EQUIPO_FUERA":{"CODCLUB":1226,"CODCLUB2":1226,"CODEQUIPO":40479,"NOMBRE_CLUB":"DON BOSCO, C.F.","NOMBRE_CLUB_URL":"don-bosco-cf","NOMBRE_EQUIPO":"DON BOSCO, C.F. B","NOMBRE_EQUIPO_URL":"don-bosco-cf-b","NOMBRE":"00100_0000105692_bosco.png","NOMBRE_ABREVIADO_URL":"3al","CODGRUPO":42202679,"TITULARES":[{"NOMBRE":"MAX GAETANO","LICENCIA":"20","DORSAL":"1","CODPARTICIPANTE":"45438424","FECHA_NACIMIENTO":2,"PORTERO":1},{"NOMBRE":"ELOI","LICENCIA":"20","DORSAL":"3","CODPARTICIPANTE":"45436127","FECHA_NACIMIENTO":2,"PORTERO":null},{"NOMBRE":"ALEX","LICENCIA":"20","DORSAL":"4","CODPARTICIPANTE":"45435750","FECHA_NACIMIENTO":2,"PORTERO":null},{"NOMBRE":"ERIC GRABRIEL","LICENCIA":"20","DORSAL":"6","CODPARTICIPANTE":"45434545","FECHA_NACIMIENTO":2,"PORTERO":null},{"NOMBRE":"JAVIER","LICENCIA":"20","DORSAL":"8","CODPARTICIPANTE":"41267611","FECHA_NACIMIENTO":1,"PORTERO":null},{"NOMBRE":"LUCAS FRANCISCO","LICENCIA":"20","DORSAL":"9","CODPARTICIPANTE":"45437971","FECHA_NACIMIENTO":2,"PORTERO":null},{"NOMBRE":"JOEN FELIP","LICENCIA":"20","DORSAL":"10","CODPARTICIPANTE":"45436635","FECHA_NACIMIENTO":2,"PORTERO":null}],"SUPLENTES":[{"NOMBRE":"ALEX","LICENCIA":"20","DORSAL":"2","CODPARTICIPANTE":"45681603","FECHA_NACIMIENTO":2,"PORTERO":null},{"NOMBRE":"HUGO","LICENCIA":"20","DORSAL":"5","CODPARTICIPANTE":"45438933","FECHA_NACIMIENTO":2,"PORTERO":null}],"COSTECNIC":{"Auxiliar":"VICTOR YARI","Entrenador Titular":"XAVIER"},"SUSTITUCIONES":[],"SANCIONES":[]}},"codacta":"3086593","titulars_local":[{"codparticipant":39702568,"codequip":32492858,"dorsal":2,"titularitats":1,"porter":null,"nom":"SAMUEL","any":2012,"partits":1,"nom_equip":"Pª BARC. CINC COPES I","colorequipacio1":"#0000FF","colorequipacio2":"#FFFF00"},{"codparticipant":42839530,"codequip":32492858,"dorsal":4,"titularitats":1,"porter":null,"nom":"GUILLERMO","any":2012,"partits":1,"nom_equip":"Pª BARC. CINC COPES I","colorequipacio1":"#0000FF","colorequipacio2":"#FFFF00"},{"codparticipant":45886400,"codequip":32492858,"dorsal":5,"titularitats":1,"porter":null,"nom":"ARNAU","any":2011,"partits":1,"nom_equip":"Pª BARC. CINC COPES I","colorequipacio1":"#0000FF","colorequipacio2":"#FFFF00"},{"codparticipant":33821875,"codequip":32492858,"dorsal":6,"titularitats":1,"porter":null,"nom":"YANZE","any":2011,"partits":1,"nom_equip":"Pª BARC. CINC COPES I","colorequipacio1":"#0000FF","colorequipacio2":"#FFFF00"},{"codparticipant":42856711,"codequip":32492858,"dorsal":8,"titularitats":1,"porter":null,"nom":"DYLAN GERARD","any":2012,"partits":1,"nom_equip":"Pª BARC. CINC COPES I","colorequipacio1":"#0000FF","colorequipacio2":"#FFFF00"},{"codparticipant":45956950,"codequip":32492858,"dorsal":9,"titularitats":1,"porter":null,"nom":"BRUC","any":2011,"partits":1,"nom_equip":"Pª BARC. CINC COPES I","colorequipacio1":"#0000FF","colorequipacio2":"#FFFF00"},{"codparticipant":46185278,"codequip":32492858,"dorsal":10,"titularitats":0,"porter":null,"nom":"LUIS GONZALO","any":2012,"partits":1,"nom_equip":"Pª BARC. CINC COPES I","colorequipacio1":"#0000FF","colorequipacio2":"#FFFF00"},{"codparticipant":46739607,"codequip":32492858,"dorsal":13,"titularitats":1,"porter":1,"nom":"BERTRAN","any":2011,"partits":1,"nom_equip":"Pª BARC. CINC COPES I","colorequipacio1":"#0000FF","colorequipacio2":"#FFFF00"}],"titulars_visitant":[{"codparticipant":45438424,"codequip":40479,"dorsal":1,"titularitats":1,"porter":1,"nom":"MAX GAETANO","any":2012,"partits":1,"nom_equip":"DON BOSCO, C.F. B","colorequipacio1":"#FFFFFF","colorequipacio2":"#2946FF"},{"codparticipant":45681603,"codequip":40479,"dorsal":2,"titularitats":0,"porter":null,"nom":"ALEX","any":2012,"partits":1,"nom_equip":"DON BOSCO, C.F. B","colorequipacio1":"#FFFFFF","colorequipacio2":"#2946FF"},{"codparticipant":45436127,"codequip":40479,"dorsal":3,"titularitats":1,"porter":null,"nom":"ELOI","any":2012,"partits":1,"nom_equip":"DON BOSCO, C.F. B","colorequipacio1":"#FFFFFF","colorequipacio2":"#2946FF"},{"codparticipant":45435750,"codequip":40479,"dorsal":4,"titularitats":1,"porter":null,"nom":"ALEX","any":2012,"partits":1,"nom_equip":"DON BOSCO, C.F. B","colorequipacio1":"#FFFFFF","colorequipacio2":"#2946FF"},{"codparticipant":45438933,"codequip":40479,"dorsal":5,"titularitats":0,"porter":null,"nom":"HUGO","any":2012,"partits":1,"nom_equip":"DON BOSCO, C.F. B","colorequipacio1":"#FFFFFF","colorequipacio2":"#2946FF"},{"codparticipant":45434545,"codequip":40479,"dorsal":6,"titularitats":1,"porter":null,"nom":"ERIC GRABRIEL","any":2012,"partits":1,"nom_equip":"DON BOSCO, C.F. B","colorequipacio1":"#FFFFFF","colorequipacio2":"#2946FF"},{"codparticipant":41267611,"codequip":40479,"dorsal":8,"titularitats":1,"porter":null,"nom":"JAVIER","any":2011,"partits":1,"nom_equip":"DON BOSCO, C.F. B","colorequipacio1":"#FFFFFF","colorequipacio2":"#2946FF"},{"codparticipant":45437971,"codequip":40479,"dorsal":9,"titularitats":1,"porter":null,"nom":"LUCAS FRANCISCO","any":2012,"partits":1,"nom_equip":"DON BOSCO, C.F. B","colorequipacio1":"#FFFFFF","colorequipacio2":"#2946FF"},{"codparticipant":45436635,"codequip":40479,"dorsal":10,"titularitats":1,"porter":null,"nom":"JOEN FELIP","any":2012,"partits":1,"nom_equip":"DON BOSCO, C.F. B","colorequipacio1":"#FFFFFF","colorequipacio2":"#2946FF"}],"menuFollowTeams":[{"label":"Aleví A","href":"/classificacio?id=44763989"},{"label":"Aleví B","href":"/classificacio?id=45021968"},{"label":"Aleví C","href":"/classificacio?id=45021534"},{"label":"Aleví D","href":"/classificacio?id=45326344"},{"label":"Aleví E","href":"/classificacio?id=45330942"}]}