{"data":[{"codparticipant":37330141,"codgroup":45021534,"nom_jugador":"SEBASTIAN","any":2011,"codacta":3037290,"codequip":40867,"dorsal":18,"titular":0,"porter":null,"codequip_local":40867,"equip_local":"VILA OLIMPICA CLUB ESP. D","escut_local":"00100_0000586311_cevo_200x200.png","colorequipacio1_local":"#2148D9","codequip_visitant":40723195,"equip_visitant":"ESCOLA DE FUTBOL STOITCHKOV-RACING SARRIA  A","escut_visitant":"00100_0000832679_stoitchkovracingsarria_200.png","colorequipacio1_visitant":"#F7F7F7","jornada":8,"gols_local":1,"gols_visitant":4}],"dataGols":[],"codparticipant":"37330141","codequip":40867,"codgroup":45021534,"menuFollowTeams":[{"label":"Aleví A","href":"/classificacio?id=44763989"},{"label":"Aleví B","href":"/classificacio?id=45021968"},{"label":"Aleví C","href":"/classificacio?id=45021534"},{"label":"Aleví D","href":"/classificacio?id=45326344"},{"label":"Aleví E","href":"/classificacio?id=45330942"}]}