{"data":[{"codparticipant":31603536,"nom_jugador":"DAVID GERARD","dorsal":11,"any":2011,"codequip":7008314,"nom_equip":"ESCOLA F ANGEL PEDRAZA A","escut":"00100_0000651412_efapedraza_200x200.png","tipus":"normal","gols":46},{"codparticipant":45021000,"nom_jugador":"ANGEL","dorsal":9,"any":2011,"codequip":7008314,"nom_equip":"ESCOLA F ANGEL PEDRAZA A","escut":"00100_0000651412_efapedraza_200x200.png","tipus":"normal","gols":30},{"codparticipant":39398994,"nom_jugador":"JAMES MICHAEL","dorsal":7,"any":2011,"codequip":7008314,"nom_equip":"ESCOLA F ANGEL PEDRAZA A","escut":"00100_0000651412_efapedraza_200x200.png","tipus":"normal","gols":29},{"codparticipant":40195737,"nom_jugador":"PABLO","dorsal":8,"any":2011,"codequip":7008314,"nom_equip":"ESCOLA F ANGEL PEDRAZA A","escut":"00100_0000651412_efapedraza_200x200.png","tipus":"normal","gols":25},{"codparticipant":32292380,"nom_jugador":"GERARD JESUS","dorsal":10,"any":2011,"codequip":7008314,"nom_equip":"ESCOLA F ANGEL PEDRAZA A","escut":"00100_0000651412_efapedraza_200x200.png","tipus":"penalti","gols":23},{"codparticipant":45573839,"nom_jugador":"YOUSSEF","dorsal":4,"any":2011,"codequip":7008314,"nom_equip":"ESCOLA F ANGEL PEDRAZA A","escut":"00100_0000651412_efapedraza_200x200.png","tipus":"normal","gols":20},{"codparticipant":31774011,"nom_jugador":"UNAI","dorsal":5,"any":2011,"codequip":7008314,"nom_equip":"ESCOLA F ANGEL PEDRAZA A","escut":"00100_0000651412_efapedraza_200x200.png","tipus":"normal","gols":10},{"codparticipant":34506262,"nom_jugador":"JULIAN OLUWAFERANMI","dorsal":2,"any":2012,"codequip":7008314,"nom_equip":"ESCOLA F ANGEL PEDRAZA A","escut":"00100_0000651412_efapedraza_200x200.png","tipus":"normal","gols":7}],"codgroup":"45021534","codequip":"7008314","menuFollowTeams":[{"label":"Aleví A","href":"/classificacio?id=44763989"},{"label":"Aleví B","href":"/classificacio?id=45021968"},{"label":"Aleví C","href":"/classificacio?id=45021534"},{"label":"Aleví D","href":"/classificacio?id=45326344"},{"label":"Aleví E","href":"/classificacio?id=45330942"}]}